README.md
setup.py
minimizer/__init__.py
minimizer/cli.py
minimizer/core.py
minimizer.egg-info/PKG-INFO
minimizer.egg-info/SOURCES.txt
minimizer.egg-info/dependency_links.txt
minimizer.egg-info/entry_points.txt
minimizer.egg-info/requires.txt
minimizer.egg-info/top_level.txt