Metadata-Version: 1.0
Name: minimizer
Version: 0.4.5
Summary: A command line tool to shrink image(s) in a directory to a specified size
Home-page: https://github.com/alexbotello/minimizer
Author: Alexander Botello
Author-email: alexander.botello@g.austincc.edu
License: MIT
Platform: UNKNOWN
